opentldr/AbstractDataRepo.py
opentldr/ContentEnrichment.py
opentldr/DataRepo.py
opentldr/DataRepoJson.py
opentldr/Domain.py
opentldr/FileSystemDataRepo.py
opentldr/KnowledgeGraph.py
opentldr/S3DataRepo.py
opentldr/Workflow.py
opentldr/__init__.py
opentldr/log.py
opentldr-1.0.0.dist-info/licenses/LICENSE
opentldr-1.0.0.dist-info/METADATA
opentldr-1.0.0.dist-info/WHEEL
opentldr-1.0.0.dist-info/top_level.txt
opentldr-1.0.0.dist-info/RECORD
