Metadata-Version: 2.4
Name: opentldr
Version: 1.0.0
Summary: An open framework for creation of a Tailored Daily Report.
Author-email: Chris Argenta <cargenta@rockfishresearch.com>
Project-URL: Source, https://github.com/RockfishResearch/OpenTLDR-Core.git
Project-URL: Issues, https://github.com/RockfishResearch/OpenTLDR-Core/issues
Project-URL: Documentation, http://www.opentldr.org/docs
Project-URL: Homepage, http://www.opentldr.org
Classifier: Programming Language :: Python :: 3
Classifier: License :: OSI Approved :: Apache Software License
Classifier: Operating System :: OS Independent
Classifier: Development Status :: 3 - Alpha
Classifier: Intended Audience :: Developers
Requires-Python: >=3.10
License-File: LICENSE
Requires-Dist: python-dotenv>=1.0.0
Requires-Dist: neo4j>=5.15.0
Requires-Dist: neomodel>=5.2.1
Requires-Dist: papermill>=2.5.0
Requires-Dist: boto3>=1.34.55
Dynamic: license-file
